pyoma/__init__.py
pyoma/common.py
pyoma/hpc.py
pyoma/application/__init__.py
pyoma/application/enrichment.py
pyoma/browser/KmerEncoder.py
pyoma/browser/OrthoXMLSplitter.py
pyoma/browser/__init__.py
pyoma/browser/ancestral_genome.py
pyoma/browser/ancestral_synteny.py
pyoma/browser/check_db_consistency.py
pyoma/browser/compute_cache.py
pyoma/browser/convert.drw
pyoma/browser/convert.py
pyoma/browser/convert_omastandalone.drw
pyoma/browser/convert_omastandalone.py
pyoma/browser/db.py
pyoma/browser/db_contrib.py
pyoma/browser/decorators.py
pyoma/browser/exceptions.py
pyoma/browser/geneontology.py
pyoma/browser/hoghelper.py
pyoma/browser/hogidmap.py
pyoma/browser/homoeologs.py
pyoma/browser/idmapper.py
pyoma/browser/linkout.py
pyoma/browser/locus_parser.py
pyoma/browser/models.py
pyoma/browser/sanitychecks.py
pyoma/browser/search.py
pyoma/browser/suffixsearch.py
pyoma/browser/synteny.py
pyoma/browser/tablefmt.py
pyoma/browser/xref_contrib.py
pyoma/browser/hogprofile/__init__.py
pyoma/browser/hogprofile/build.py
pyoma/browser/hogprofile/hashutils.py
pyoma/browser/hogprofile/pyhamutils.py
pyoma/browser/hogprofile/query.py
pyoma/browser/hogprofile/tree_helper.py
pyoma/inference/__init__.py
pyoma/inference/algo.py
pyoma/inference/db.py
pyoma/inference/tabledef.py
pyoma/orthoxml/__init__.py
pyoma/orthoxml/compare.py
pyoma-0.13.4.data/scripts/importdata.py
pyoma-0.13.4.data/scripts/map_to_closest_seq
pyoma-0.13.4.data/scripts/oma2hdf
pyoma-0.13.4.dist-info/LICENSE
pyoma-0.13.4.dist-info/METADATA
pyoma-0.13.4.dist-info/WHEEL
pyoma-0.13.4.dist-info/top_level.txt
pyoma-0.13.4.dist-info/RECORD
